torchsubband/__init__.py
torchsubband/main.py
torchsubband/pqmf.py
torchsubband-0.0.9.dist-info/LICENSE
torchsubband-0.0.9.dist-info/METADATA
torchsubband-0.0.9.dist-info/WHEEL
torchsubband-0.0.9.dist-info/top_level.txt
torchsubband-0.0.9.dist-info/RECORD
