Metadata-Version: 2.1
Name: torchsubband
Version: 0.0.9
Summary: This package is written for subband operations.
Home-page: https://github.com/haoheliu/torchsubband
Author: Haohe Liu
Author-email: haoheliu@gmail.com
License: MIT
Classifier: License :: OSI Approved :: MIT License
Classifier: Programming Language :: Python
Classifier: Programming Language :: Python :: 3
Classifier: Programming Language :: Python :: 3.7
Classifier: Programming Language :: Python :: Implementation :: CPython
Classifier: Programming Language :: Python :: Implementation :: PyPy
Requires-Python: >=3.6.0
License-File: LICENSE
Requires-Dist: torch (>=1.8.0)
Requires-Dist: torchlibrosa (<=0.0.9,>=0.0.7)
